masked/__init__.py
masked-1.0.1.dist-info/LICENSE
masked-1.0.1.dist-info/METADATA
masked-1.0.1.dist-info/WHEEL
masked-1.0.1.dist-info/top_level.txt
masked-1.0.1.dist-info/RECORD
